penzai/__init__.py
penzai/core/__init__.py
penzai/core/auto_order_types.py
penzai/core/named_axes.py
penzai/core/partitioning.py
penzai/core/random_stream.py
penzai/core/selectors.py
penzai/core/shapecheck.py
penzai/core/struct.py
penzai/core/syntactic_sugar.py
penzai/core/tree_util.py
penzai/core/variables.py
penzai/core/_treescope_handlers/__init__.py
penzai/core/_treescope_handlers/named_axes_handlers.py
penzai/core/_treescope_handlers/selection_rendering.py
penzai/core/_treescope_handlers/shapecheck_handlers.py
penzai/core/_treescope_handlers/struct_handler.py
penzai/deprecated/__init__.py
penzai/deprecated/v1/__init__.py
penzai/deprecated/v1/core/__init__.py
penzai/deprecated/v1/core/layer.py
penzai/deprecated/v1/core/random_stream.py
penzai/deprecated/v1/core/_treescope_handlers/__init__.py
penzai/deprecated/v1/core/_treescope_handlers/layer_handler.py
penzai/deprecated/v1/data_effects/__init__.py
penzai/deprecated/v1/data_effects/_treescope_handlers.py
penzai/deprecated/v1/data_effects/effect_base.py
penzai/deprecated/v1/data_effects/local_state.py
penzai/deprecated/v1/data_effects/random.py
penzai/deprecated/v1/data_effects/side_input.py
penzai/deprecated/v1/data_effects/side_output.py
penzai/deprecated/v1/example_models/__init__.py
penzai/deprecated/v1/example_models/simple_mlp.py
penzai/deprecated/v1/example_models/gemma/__init__.py
penzai/deprecated/v1/example_models/gemma/model_core.py
penzai/deprecated/v1/example_models/gemma/sampling_mode.py
penzai/deprecated/v1/example_models/gemma/simple_decoding_loop.py
penzai/deprecated/v1/nn/__init__.py
penzai/deprecated/v1/nn/attention.py
penzai/deprecated/v1/nn/basic_ops.py
penzai/deprecated/v1/nn/combinators.py
penzai/deprecated/v1/nn/dropout.py
penzai/deprecated/v1/nn/embeddings.py
penzai/deprecated/v1/nn/grouping.py
penzai/deprecated/v1/nn/linear_and_affine.py
penzai/deprecated/v1/nn/parameters.py
penzai/deprecated/v1/nn/standardization.py
penzai/deprecated/v1/pz/__init__.py
penzai/deprecated/v1/pz/de.py
penzai-0.2.5.dist-info/licenses/LICENSE
penzai-0.2.5.dist-info/WHEEL
penzai-0.2.5.dist-info/METADATA
penzai-0.2.5.dist-info/RECORD
