Metadata-Version: 2.4
Name: penzai
Version: 0.2.5
Summary: Penzai: A JAX research toolkit for building, editing, and visualizing neural networks.
Keywords: 
Author-email: The Penzai Authors <penzai-dev@google.com>
Requires-Python: >=3.10
Classifier: Programming Language :: Python :: 3
Classifier: Programming Language :: Python :: 3 :: Only
Classifier: License :: OSI Approved :: Apache Software License
Classifier: Intended Audience :: Science/Research
License-File: LICENSE
Requires-Dist: absl-py>=1.4.0
Requires-Dist: jax>=0.4.23
Requires-Dist: numpy>=1.25.2
Requires-Dist: ordered_set>=4.1.0
Requires-Dist: treescope>=0.1.9
Requires-Dist: typing_extensions>=4.2
Requires-Dist: pylint>=2.6.0 ; extra == "dev"
Requires-Dist: pyink>=24.3.0 ; extra == "dev"
Requires-Dist: ipython ; extra == "dev"
Requires-Dist: jupyter ; extra == "dev"
Requires-Dist: pytest>=8.2.2 ; extra == "dev"
Requires-Dist: pytype ; extra == "dev"
Requires-Dist: ipython ; extra == "docs"
Requires-Dist: flax>=0.8.2 ; extra == "docs"
Requires-Dist: optax ; extra == "docs"
Requires-Dist: setuptools ; extra == "docs"
Requires-Dist: sphinx>=6.0.0,<7.3.0 ; extra == "docs"
Requires-Dist: sphinx-book-theme>=1.0.1 ; extra == "docs"
Requires-Dist: sphinxcontrib-katex ; extra == "docs"
Requires-Dist: ipython>=8.8.0 ; extra == "docs"
Requires-Dist: myst-nb>=1.0.0 ; extra == "docs"
Requires-Dist: myst-parser>=3.0.1 ; extra == "docs"
Requires-Dist: matplotlib>=3.5.0 ; extra == "docs"
Requires-Dist: packaging==24.1 ; extra == "docs"
Requires-Dist: sphinx-collections>=0.0.1 ; extra == "docs"
Requires-Dist: sphinx_contributors ; extra == "docs"
Requires-Dist: sphinx-hoverxref ; extra == "docs"
Requires-Dist: jax[cpu]>=0.4.23 ; extra == "docs"
Requires-Dist: ipython ; extra == "extras"
Requires-Dist: flax>=0.8.2 ; extra == "extras"
Requires-Dist: optax ; extra == "extras"
Requires-Dist: torch ; extra == "extras"
Requires-Dist: transformers>=4.41.2 ; extra == "extras"
Requires-Dist: ipython ; extra == "notebook"
Requires-Dist: flax>=0.8.2 ; extra == "notebook"
Requires-Dist: optax ; extra == "notebook"
Requires-Dist: orbax-checkpoint ; extra == "notebook"
Requires-Dist: palettable ; extra == "notebook"
Project-URL: homepage, https://github.com/google-deepmind/penzai
Project-URL: repository, https://github.com/google-deepmind/penzai
Provides-Extra: dev
Provides-Extra: docs
Provides-Extra: extras
Provides-Extra: notebook
